src/__init__.py
src/options.py
src/pyyt.py
src/utils.py
pyyt_cli-0.2.2.dist-info/LICENSE
pyyt_cli-0.2.2.dist-info/METADATA
pyyt_cli-0.2.2.dist-info/WHEEL
pyyt_cli-0.2.2.dist-info/entry_points.txt
pyyt_cli-0.2.2.dist-info/top_level.txt
pyyt_cli-0.2.2.dist-info/RECORD
