Metadata-Version: 2.1
Name: pyyt-cli
Version: 0.2.2
Summary: Python script to download videos as audio from a given YouTube playlist/video
Home-page: https://github.com/patillacode/pyyt
Author: Patilla Code
Author-email: patillacode@gmail.com
License: Apache 2.0
Keywords: converter,audio,youtube,download,mp3
Classifier: Intended Audience :: Developers
Classifier: Topic :: Utilities
Classifier: License :: Public Domain
Classifier: Natural Language :: English
Classifier: Operating System :: OS Independent
Classifier: Programming Language :: Python :: 3.11
License-File: LICENSE
Requires-Dist: pyfiglet
Requires-Dist: simple-term-menu
Requires-Dist: yt-dlp
Requires-Dist: termcolor
Provides-Extra: test
Requires-Dist: coverage ; extra == 'test'
Requires-Dist: pytest ; extra == 'test'
Requires-Dist: pytest-cov ; extra == 'test'
Requires-Dist: mock ; extra == 'test'
